[
    {
        "英単語": "embarrassing",
        "意味": "恥ずかしい",
        "品詞": "形容詞",
        "例文": "That was an embarrassing mistake."
    },
    {
        "英単語": "moment",
        "意味": "瞬間、出来事",
        "品詞": "名詞",
        "例文": "This was a special moment for me."
    },
    {
        "英単語": "decide",
        "意味": "決める",
        "品詞": "動詞",
        "例文": "I decided to study English seriously."
    },
    {
        "英単語": "adult",
        "意味": "大人",
        "品詞": "名詞",
        "例文": "She became an adult at 18."
    },
    {
        "英単語": "quickly",
        "意味": "すぐに",
        "品詞": "副詞",
        "例文": "He quickly understood the problem."
    },
    {
        "英単語": "invite",
        "意味": "招待する",
        "品詞": "動詞",
        "例文": "They invited me to the party."
    },
    {
        "英単語": "stage",
        "意味": "舞台",
        "品詞": "名詞",
        "例文": "She went up on the stage."
    },
    {
        "英単語": "congratulations",
        "意味": "おめでとう",
        "品詞": "名詞",
        "例文": "Congratulations on your success!"
    },
    {
        "英単語": "realize",
        "意味": "気づく",
        "品詞": "動詞",
        "例文": "I realized my mistake later."
    },
    {
        "英単語": "pregnant",
        "意味": "妊娠している",
        "品詞": "形容詞",
        "例文": "She is pregnant with her first child."
    }
]
